fastapi_i18n/__init__.py
fastapi_i18n/main.py
fastapi_i18n-0.12.0.dist-info/licenses/COPYING
fastapi_i18n-0.12.0.dist-info/licenses/COPYING.LESSER
fastapi_i18n-0.12.0.dist-info/WHEEL
fastapi_i18n-0.12.0.dist-info/METADATA
fastapi_i18n-0.12.0.dist-info/RECORD
