Metadata-Version: 2.4
Name: fastapi-i18n
Version: 0.12.0
Summary: FastAPI Internationalization (i18n)
Author: HeiGIT ohsome team
Author-email: HeiGIT ohsome team <ohsome@heigit.org>
License-Expression: LGPL-3.0-only
License-File: COPYING
License-File: COPYING.LESSER
Classifier: Framework :: FastAPI
Classifier: Intended Audience :: Developers
Classifier: Intended Audience :: Science/Research
Classifier: License :: OSI Approved :: GNU Lesser General Public License v3 (LGPLv3)
Classifier: Programming Language :: Python :: 3 :: Only
Classifier: Programming Language :: Python :: 3.11
Classifier: Programming Language :: Python :: 3.12
Classifier: Programming Language :: Python :: 3.13
Classifier: Topic :: Scientific/Engineering :: GIS
Classifier: Topic :: Software Development :: Libraries :: Python Modules
Requires-Dist: babel>=2.17.0
Requires-Dist: fastapi>=0.109.2
Requires-Dist: httpx>=0.23.0
Requires-Python: >=3.11, <3.14
Project-URL: Documentation, https://github.com/GIScience/fastapi-i18n/blob/main/README.md
Project-URL: Homepage, https://ohsome.org/
Project-URL: Issues, https://github.com/GIScience/fastapi-i18n/issues
Project-URL: Repository, https://github.com/GIScience/fastapi-i18n
